discord_python/ApplicationCommands.py
discord_python/Client.py
discord_python/Enums.py
discord_python/InteractionResponder.py
discord_python/Logger.py
discord_python/Message.py
discord_python/__init__.py
discord_python_sniperthrilla-0.0.6.dist-info/METADATA
discord_python_sniperthrilla-0.0.6.dist-info/WHEEL
discord_python_sniperthrilla-0.0.6.dist-info/licenses/LICENSE
discord_python_sniperthrilla-0.0.6.dist-info/RECORD
