Metadata-Version: 2.1
Name: discord_python_SniperThrilla
Version: 0.0.6
Summary: A small example package
Project-URL: Homepage, https://github.com/SniperThrilla/discord-python
Project-URL: Bug Tracker, https://github.com/SniperThrilla/discord-python/issues
Author-email: Jayden Young <jayden.tyler.young@gmail.com>
License-File: LICENSE
Classifier: License :: OSI Approved :: GNU General Public License v3 (GPLv3)
Classifier: Operating System :: OS Independent
Classifier: Programming Language :: Python :: 3
Requires-Python: >=3.10
